occgpu/__init__.py
occgpu/cli.py
occgpu/core.py
occgpu/occ.py
occgpu/utils.py
occgpu-0.1.0.dist-info/METADATA
occgpu-0.1.0.dist-info/WHEEL
occgpu-0.1.0.dist-info/entry_points.txt
occgpu-0.1.0.dist-info/top_level.txt
occgpu-0.1.0.dist-info/RECORD
