Metadata-Version: 2.4
Name: occgpu
Version: 0.1.0
Summary: A tool to occupy free GPU memory and prevent others from using it
Home-page: https://github.com/howccc/occgpu
Author: Three Liu
Author-email: liushurui66666@example.com
Classifier: Programming Language :: Python :: 3
Classifier: License :: OSI Approved :: MIT License
Classifier: Operating System :: Unix
Classifier: Topic :: System :: Monitoring
Requires-Python: >=3.6
Requires-Dist: numpy
Dynamic: author
Dynamic: author-email
Dynamic: classifier
Dynamic: description
Dynamic: description-content-type
Dynamic: home-page
Dynamic: requires-dist
Dynamic: requires-python
Dynamic: summary
